guerrilla_aaron-0.1.8.dist-info/METADATA
guerrilla_aaron-0.1.8.dist-info/WHEEL
guerrilla_aaron/.gitignore
guerrilla_aaron/__init__.py
guerrilla_aaron/atb/const.py
guerrilla_aaron/atb/service/__init__.py
guerrilla_aaron/atb/service/bird.py
guerrilla_aaron/atb/service/ca.py
guerrilla_aaron/atb/service/hping3.py
guerrilla_aaron/atb/service/mail_server.py
guerrilla_aaron/atb/service/nmcli.py
guerrilla_aaron/atb/service/pktmgmt.py
guerrilla_aaron/atb/service/radius.py
guerrilla_aaron/atb/service/scapy.py
guerrilla_aaron/atb/service/scapy_template/arp_script.py
guerrilla_aaron/atb/service/scapy_template/broadcast_script.py
guerrilla_aaron/atb/service/scapy_template/igmp_script.py
guerrilla_aaron/atb/service/scapy_template/multicast_script.py
guerrilla_aaron/atb/service/scapy_template/rip_script.py
guerrilla_aaron/atb/service/scapy_template/rstp_script.py
guerrilla_aaron/atb/service/scapy_template/vrrp_script.py
guerrilla_aaron/atb/service/shellcmd.py
guerrilla_aaron/atb/service/snmp.py
guerrilla_aaron/atb/service/syslog.py
guerrilla_aaron/atb/service/tftp.py
guerrilla_aaron/atb/service/trex.py
guerrilla_aaron/atb/service/tshark.py
guerrilla_aaron/atb/service/uictrl.py
guerrilla_aaron/host.py
guerrilla_aaron/ixia.py
guerrilla_aaron/mdc/__init__.py
guerrilla_aaron/mdc/router/cli/__init__.py
guerrilla_aaron/mdc/router/cli/common_func.py
guerrilla_aaron/mdc/router/cli/md_edr8010/__init__.py
guerrilla_aaron/mdc/router/cli/md_edr8010/edr8010_v3.py
guerrilla_aaron/mdc/router/cli/md_edr810/__init__.py
guerrilla_aaron/mdc/router/cli/md_edr810/edr810_v5.py
guerrilla_aaron/mdc/router/cli/md_edrg9010/__init__.py
guerrilla_aaron/mdc/router/cli/md_edrg9010/edrg9010_v2.py
guerrilla_aaron/mdc/router/cli/md_edrg9010/edrg9010_v3.py
guerrilla_aaron/mdc/router/cli/md_tn5916/__init__.py
guerrilla_aaron/mdc/router/cli/md_tn5916/tn5916_v3.py
guerrilla_aaron/mdc/router/cli/md_tn5916/tn5916_v3_0_27.py
guerrilla_aaron/mdc/router/cli/rp_api/__init__.py
guerrilla_aaron/mdc/router/cli/rp_api/rp_api.py
guerrilla_aaron/mdc/router/cli/rp_base/__init__.py
guerrilla_aaron-0.1.8.dist-info/RECORD
