Metadata-Version: 2.1
Name: guerrilla_aaron
Version: 0.1.8
Summary: demo
Author-Email: aaronkc_wu <aaronkc_wu@moxa.com>
License: MIT
Requires-Python: >=3.12
Requires-Dist: allure-behave==2.12.0
Requires-Dist: async-generator==1.10
Requires-Dist: async-lru==1.0.2
Requires-Dist: async-timeout==4.0.2
Requires-Dist: attrs==21.4.0
Requires-Dist: behave-html-formatter==0.9.10
Requires-Dist: certifi==2021.10.8
Requires-Dist: chardet==4.0.0
Requires-Dist: charset-normalizer==2.0.11
Requires-Dist: colorama==0.4.4
Requires-Dist: cryptography==36.0.1
Requires-Dist: cucumber-tag-expressions==4.1.0
Requires-Dist: cython==0.29.34
Requires-Dist: cffi==1.16.0
Requires-Dist: dill==0.3.4
Requires-Dist: distro==1.6.0
Requires-Dist: et-xmlfile==1.1.0
Requires-Dist: future==0.18.2
Requires-Dist: gitdb==4.0.9
Requires-Dist: GitPython==3.1.18
Requires-Dist: h11==0.13.0
Requires-Dist: idna==3.3
Requires-Dist: iso8601==1.0.2
Requires-Dist: Jinja2==3.0.3
Requires-Dist: junit-xml==1.9
Requires-Dist: lxml==4.9.3
Requires-Dist: MarkupSafe==2.0.1
Requires-Dist: openpyxl==3.0.9
Requires-Dist: outcome==1.1.0
Requires-Dist: parse==1.19.0
Requires-Dist: parse-type==0.6.0
Requires-Dist: pathspec==0.9.0
Requires-Dist: pexpect==4.8.0
Requires-Dist: ptyprocess==0.7.0
Requires-Dist: py==1.11.0
Requires-Dist: pycparser==2.21
Requires-Dist: pyOpenSSL==22.0.0
Requires-Dist: pyserial==3.5
Requires-Dist: pyshark==0.4.3
Requires-Dist: python-engineio==3.14.2
Requires-Dist: python-socketio==4.6.1
Requires-Dist: PyYAML==6.0.1
Requires-Dist: requests==2.27.1
Requires-Dist: selenium==4.1.0
Requires-Dist: six==1.16.0
Requires-Dist: smmap==5.0.0
Requires-Dist: sniffio==1.2.0
Requires-Dist: sortedcontainers==2.4.0
Requires-Dist: textfsm==1.1.3
Requires-Dist: trio==0.19.0
Requires-Dist: trio-websocket==0.9.2
Requires-Dist: urllib3==1.26.8
Requires-Dist: wsproto==1.0.0
Requires-Dist: ixnetwork_restpy
